ros_msg_transform/__init__.py
ros_msg_transform/transform.py
ros_msg_transform-0.3.1.dist-info/licenses/LICENSE
ros_msg_transform-0.3.1.dist-info/METADATA
ros_msg_transform-0.3.1.dist-info/WHEEL
ros_msg_transform-0.3.1.dist-info/top_level.txt
ros_msg_transform-0.3.1.dist-info/RECORD
