Metadata-Version: 2.4
Name: ros-msg-transform
Version: 0.3.1
Summary: Library to transform ROS messages to Python structures
Author-email: Konstantinos Panayiotou <klpanagi@ece.auth.gr>
License: MIT
Project-URL: homepage, https://github.com/robotics4all/ros-msg-transform
Project-URL: repository, https://github.com/robotics4all/ros-msg-transform
Keywords: ros,iot,cps
Classifier: Development Status :: 4 - Beta
Classifier: Intended Audience :: Developers
Classifier: License :: OSI Approved :: MIT License
Classifier: Natural Language :: English
Classifier: Programming Language :: Python :: 3
Classifier: Programming Language :: Python :: 3.8
Requires-Python: >=3.8
License-File: LICENSE
Requires-Dist: setuptools>=21.0.0
Provides-Extra: dev
Requires-Dist: bump2version>=0.5.11; extra == "dev"
Requires-Dist: pytest>=7.0.0; extra == "dev"
Provides-Extra: test
Requires-Dist: pytest; extra == "test"
Requires-Dist: pytest-cov; extra == "test"
Dynamic: license-file
